aprs2mqtt/APRS2MQTT.py
aprs2mqtt/Exceptions.py
aprs2mqtt/MQTT2APRS.py
aprs2mqtt/Message.py
aprs2mqtt/Util.py
aprs2mqtt/__init__.py
aprs2mqtt/aprs2mqttmsg.py
aprs2mqtt/mqtt2aprsmsg.py
aprs2mqtt-0.9.4.dist-info/licenses/LICENSE
aprs2mqtt-0.9.4.dist-info/METADATA
aprs2mqtt-0.9.4.dist-info/WHEEL
aprs2mqtt-0.9.4.dist-info/entry_points.txt
aprs2mqtt-0.9.4.dist-info/top_level.txt
aprs2mqtt-0.9.4.dist-info/RECORD
