Metadata-Version: 2.4
Name: aprs2mqtt
Version: 0.9.4
Summary: Collection of utilities to interface APRS and MQTT
Author-email: Jason McCormick <jason@mfamily.org>
License-Expression: MIT
Project-URL: Homepage, https://github.com/jxmx/aprs2mqtt
Project-URL: Issues, https://github.com/jxmx/aprs2mqtt/issues
Classifier: Programming Language :: Python :: 3
Classifier: Operating System :: OS Independent
Requires-Python: >=3.6
License-File: LICENSE
Dynamic: license-file
